ifconf/__init__.py
ifconf/__main__.py
ifconf/common.py
ifconf/config.py
ifconf/loader.py
ifconf/loggingconf.py
ifconf/main.py
ifconf/module.py
ifconf/printconf.py
ifconf-0.0.16.dist-info/LICENSE.txt
ifconf-0.0.16.dist-info/METADATA
ifconf-0.0.16.dist-info/WHEEL
ifconf-0.0.16.dist-info/top_level.txt
ifconf-0.0.16.dist-info/RECORD
