Metadata-Version: 2.1
Name: ifconf
Version: 0.0.16
Summary: Integrated Framework for Configuration
Home-page: https://github.com/iflb/ifconf
Author: teppei@iflab.tokyo
Author-email: teppei@iflab.tokyo
License: UNKNOWN
Project-URL: Project Owner, http://www.pcl.cs.waseda.ac.jp/
Project-URL: Funding, https://www.waseda.jp/inst/gcs/news/2019/11/29/870/
Keywords: configuration argparse configparser logging
Platform: UNKNOWN
Classifier: Development Status :: 2 - Pre-Alpha
Classifier: Intended Audience :: Developers
Classifier: Topic :: Software Development :: Build Tools
Classifier: License :: OSI Approved :: MIT License
Classifier: Programming Language :: Python :: 3
Classifier: Operating System :: OS Independent
Requires-Python: >=3.5
Requires-Dist: configparser
